mulimgviewer/__init__.py
mulimgviewer/__main__.py
mulimgviewer/_version.py
mulimgviewer/mulimgviewer.png
mulimgviewer/font/using/01_Arial.ttf
mulimgviewer/font/using/02_Arial-Bold.ttf
mulimgviewer/font/using/03_Arial-Italic.ttf
mulimgviewer/font/using/04_Calibri-Light.ttf
mulimgviewer/font/using/05_Calibri-Italic.ttf
mulimgviewer/font/using/06_Calibri-Bold.ttf
mulimgviewer/font/using/07_Fira-Code.ttf
mulimgviewer/font/using/08_Song.ttc
mulimgviewer/font/using/09_Times-New-Roman.ttf
mulimgviewer/font/using/10_WenQuanYi-Micro-Hei.ttf
mulimgviewer/gui/about_gui.fbp
mulimgviewer/gui/about_gui.py
mulimgviewer/gui/index_table_gui.fbp
mulimgviewer/gui/index_table_gui.py
mulimgviewer/gui/main_gui.fbp
mulimgviewer/gui/main_gui.py
mulimgviewer/gui/path_select_gui.fbp
mulimgviewer/gui/path_select_gui.py
mulimgviewer/src/about.py
mulimgviewer/src/data.py
mulimgviewer/src/index_table.py
mulimgviewer/src/main.py
mulimgviewer/src/path_select.py
mulimgviewer/src/utils.py
mulimgviewer/src/utils_img.py
mulimgviewer-3.9.10.dist-info/LICENSE
mulimgviewer-3.9.10.dist-info/METADATA
mulimgviewer-3.9.10.dist-info/WHEEL
mulimgviewer-3.9.10.dist-info/entry_points.txt
mulimgviewer-3.9.10.dist-info/top_level.txt
mulimgviewer-3.9.10.dist-info/RECORD
