Metadata-Version: 2.1
Name: mulimgviewer
Version: 3.9.10
Summary: A multi-image viewer that can open multiple images in one interface, which is convenient for image comparison and image stitching.
Author-email: nachifur <1476879092@qq.com>
License: GPL v3
Project-URL: Homepage, https://mulimgviewer.readthedocs.io
Project-URL: Download, https://github.com/nachifur/mulimgviewer/releases
Project-URL: Bug Report, https://github.com/nachifur/mulimgviewer/issues
Project-URL: Source, https://github.com/nachifur/mulimgviewer
Keywords: computer-vision,deep-learning,ubuntu,viewer,parallel,python3,image-viewer,windows10,image-comparison,image-stitching,opencas,picture-viewer,multiple-imageview,multiple-images,multiple-image-comparison
Classifier: Development Status :: 3 - Alpha
Classifier: Intended Audience :: Developers
Classifier: Topic :: Software Development :: Build Tools
Classifier: License :: OSI Approved :: GNU General Public License v3 (GPLv3)
Classifier: Operating System :: Microsoft :: Windows
Classifier: Operating System :: POSIX
Classifier: Operating System :: Unix
Classifier: Operating System :: MacOS
Classifier: Programming Language :: Python :: 3 :: Only
Classifier: Programming Language :: Python :: 3
Classifier: Programming Language :: Python :: 3.7
Classifier: Programming Language :: Python :: 3.8
Classifier: Programming Language :: Python :: 3.9
Classifier: Programming Language :: Python :: 3.10
Classifier: Programming Language :: Python :: 3.11
Classifier: Programming Language :: Python :: Implementation :: CPython
Classifier: Programming Language :: Python :: Implementation :: PyPy
Requires-Python: >=3.7
License-File: LICENSE
Requires-Dist: numpy
Requires-Dist: piexif
Requires-Dist: pillow
Requires-Dist: requests
Requires-Dist: wxpython
Provides-Extra: dev
Requires-Dist: pre-commit ; extra == 'dev'
